Classfile /home/unfamily/IdeaProjects/Replication-RS-Bridge/temp-extract/com/refinedmods/refinedstorage/api/network/impl/node/iface/InterfaceTransferResult.class
  Last modified 6 apr 2025; size 1664 bytes
  SHA-256 checksum da441a808ebec312a7b22481ccf670454c037b1fe8f2114b701af22692e280c3
  Compiled from "InterfaceTransferResult.java"
public final class com.refinedmods.refinedstorage.api.network.impl.node.iface.InterfaceTransferResult extends java.lang.Enum<com.refinedmods.refinedstorage.api.network.impl.node.iface.InterfaceTransferResult>
  minor version: 0
  major version: 65
  flags: (0x4031) ACC_PUBLIC, ACC_FINAL, ACC_SUPER, ACC_ENUM
  this_class: #1                          // com/refinedmods/refinedstorage/api/network/impl/node/iface/InterfaceTransferResult
  super_class: #29                        // java/lang/Enum
  interfaces: 0, fields: 6, methods: 5, attributes: 2
Constant pool:
   #1 = Class              #2             // com/refinedmods/refinedstorage/api/network/impl/node/iface/InterfaceTransferResult
   #2 = Utf8               com/refinedmods/refinedstorage/api/network/impl/node/iface/InterfaceTransferResult
   #3 = Fieldref           #1.#4          // com/refinedmods/refinedstorage/api/network/impl/node/iface/InterfaceTransferResult.EXPORTED:Lcom/refinedmods/refinedstorage/api/network/impl/node/iface/InterfaceTransferResult;
   #4 = NameAndType        #5:#6          // EXPORTED:Lcom/refinedmods/refinedstorage/api/network/impl/node/iface/InterfaceTransferResult;
   #5 = Utf8               EXPORTED
   #6 = Utf8               Lcom/refinedmods/refinedstorage/api/network/impl/node/iface/InterfaceTransferResult;
   #7 = Fieldref           #1.#8          // com/refinedmods/refinedstorage/api/network/impl/node/iface/InterfaceTransferResult.RESOURCE_MISSING:Lcom/refinedmods/refinedstorage/api/network/impl/node/iface/InterfaceTransferResult;
   #8 = NameAndType        #9:#6          // RESOURCE_MISSING:Lcom/refinedmods/refinedstorage/api/network/impl/node/iface/InterfaceTransferResult;
   #9 = Utf8               RESOURCE_MISSING
  #10 = Fieldref           #1.#11         // com/refinedmods/refinedstorage/api/network/impl/node/iface/InterfaceTransferResult.STORAGE_DOES_NOT_ACCEPT_RESOURCE:Lcom/refinedmods/refinedstorage/api/network/impl/node/iface/InterfaceTransferResult;
  #11 = NameAndType        #12:#6         // STORAGE_DOES_NOT_ACCEPT_RESOURCE:Lcom/refinedmods/refinedstorage/api/network/impl/node/iface/InterfaceTransferResult;
  #12 = Utf8               STORAGE_DOES_NOT_ACCEPT_RESOURCE
  #13 = Fieldref           #1.#14         // com/refinedmods/refinedstorage/api/network/impl/node/iface/InterfaceTransferResult.AUTOCRAFTING_STARTED:Lcom/refinedmods/refinedstorage/api/network/impl/node/iface/InterfaceTransferResult;
  #14 = NameAndType        #15:#6         // AUTOCRAFTING_STARTED:Lcom/refinedmods/refinedstorage/api/network/impl/node/iface/InterfaceTransferResult;
  #15 = Utf8               AUTOCRAFTING_STARTED
  #16 = Fieldref           #1.#17         // com/refinedmods/refinedstorage/api/network/impl/node/iface/InterfaceTransferResult.AUTOCRAFTING_MISSING_RESOURCES:Lcom/refinedmods/refinedstorage/api/network/impl/node/iface/InterfaceTransferResult;
  #17 = NameAndType        #18:#6         // AUTOCRAFTING_MISSING_RESOURCES:Lcom/refinedmods/refinedstorage/api/network/impl/node/iface/InterfaceTransferResult;
  #18 = Utf8               AUTOCRAFTING_MISSING_RESOURCES
  #19 = Fieldref           #1.#20         // com/refinedmods/refinedstorage/api/network/impl/node/iface/InterfaceTransferResult.$VALUES:[Lcom/refinedmods/refinedstorage/api/network/impl/node/iface/InterfaceTransferResult;
  #20 = NameAndType        #21:#22        // $VALUES:[Lcom/refinedmods/refinedstorage/api/network/impl/node/iface/InterfaceTransferResult;
  #21 = Utf8               $VALUES
  #22 = Utf8               [Lcom/refinedmods/refinedstorage/api/network/impl/node/iface/InterfaceTransferResult;
  #23 = Methodref          #24.#25        // "[Lcom/refinedmods/refinedstorage/api/network/impl/node/iface/InterfaceTransferResult;".clone:()Ljava/lang/Object;
  #24 = Class              #22            // "[Lcom/refinedmods/refinedstorage/api/network/impl/node/iface/InterfaceTransferResult;"
  #25 = NameAndType        #26:#27        // clone:()Ljava/lang/Object;
  #26 = Utf8               clone
  #27 = Utf8               ()Ljava/lang/Object;
  #28 = Methodref          #29.#30        // java/lang/Enum.valueOf:(Ljava/lang/Class;Ljava/lang/String;)Ljava/lang/Enum;
  #29 = Class              #31            // java/lang/Enum
  #30 = NameAndType        #32:#33        // valueOf:(Ljava/lang/Class;Ljava/lang/String;)Ljava/lang/Enum;
  #31 = Utf8               java/lang/Enum
  #32 = Utf8               valueOf
  #33 = Utf8               (Ljava/lang/Class;Ljava/lang/String;)Ljava/lang/Enum;
  #34 = Methodref          #29.#35        // java/lang/Enum."<init>":(Ljava/lang/String;I)V
  #35 = NameAndType        #36:#37        // "<init>":(Ljava/lang/String;I)V
  #36 = Utf8               <init>
  #37 = Utf8               (Ljava/lang/String;I)V
  #38 = String             #5             // EXPORTED
  #39 = Methodref          #1.#35         // com/refinedmods/refinedstorage/api/network/impl/node/iface/InterfaceTransferResult."<init>":(Ljava/lang/String;I)V
  #40 = String             #9             // RESOURCE_MISSING
  #41 = String             #12            // STORAGE_DOES_NOT_ACCEPT_RESOURCE
  #42 = String             #15            // AUTOCRAFTING_STARTED
  #43 = String             #18            // AUTOCRAFTING_MISSING_RESOURCES
  #44 = Methodref          #1.#45         // com/refinedmods/refinedstorage/api/network/impl/node/iface/InterfaceTransferResult.$values:()[Lcom/refinedmods/refinedstorage/api/network/impl/node/iface/InterfaceTransferResult;
  #45 = NameAndType        #46:#47        // $values:()[Lcom/refinedmods/refinedstorage/api/network/impl/node/iface/InterfaceTransferResult;
  #46 = Utf8               $values
  #47 = Utf8               ()[Lcom/refinedmods/refinedstorage/api/network/impl/node/iface/InterfaceTransferResult;
  #48 = Utf8               values
  #49 = Utf8               Code
  #50 = Utf8               LineNumberTable
  #51 = Utf8               (Ljava/lang/String;)Lcom/refinedmods/refinedstorage/api/network/impl/node/iface/InterfaceTransferResult;
  #52 = Utf8               LocalVariableTable
  #53 = Utf8               name
  #54 = Utf8               Ljava/lang/String;
  #55 = Utf8               MethodParameters
  #56 = Utf8               this
  #57 = Utf8               Signature
  #58 = Utf8               ()V
  #59 = Utf8               <clinit>
  #60 = Utf8               Ljava/lang/Enum<Lcom/refinedmods/refinedstorage/api/network/impl/node/iface/InterfaceTransferResult;>;
  #61 = Utf8               SourceFile
  #62 = Utf8               InterfaceTransferResult.java
{
  public static final com.refinedmods.refinedstorage.api.network.impl.node.iface.InterfaceTransferResult EXPORTED;
    descriptor: Lcom/refinedmods/refinedstorage/api/network/impl/node/iface/InterfaceTransferResult;
    flags: (0x4019) ACC_PUBLIC, ACC_STATIC, ACC_FINAL, ACC_ENUM

  public static final com.refinedmods.refinedstorage.api.network.impl.node.iface.InterfaceTransferResult RESOURCE_MISSING;
    descriptor: Lcom/refinedmods/refinedstorage/api/network/impl/node/iface/InterfaceTransferResult;
    flags: (0x4019) ACC_PUBLIC, ACC_STATIC, ACC_FINAL, ACC_ENUM

  public static final com.refinedmods.refinedstorage.api.network.impl.node.iface.InterfaceTransferResult STORAGE_DOES_NOT_ACCEPT_RESOURCE;
    descriptor: Lcom/refinedmods/refinedstorage/api/network/impl/node/iface/InterfaceTransferResult;
    flags: (0x4019) ACC_PUBLIC, ACC_STATIC, ACC_FINAL, ACC_ENUM

  public static final com.refinedmods.refinedstorage.api.network.impl.node.iface.InterfaceTransferResult AUTOCRAFTING_STARTED;
    descriptor: Lcom/refinedmods/refinedstorage/api/network/impl/node/iface/InterfaceTransferResult;
    flags: (0x4019) ACC_PUBLIC, ACC_STATIC, ACC_FINAL, ACC_ENUM

  public static final com.refinedmods.refinedstorage.api.network.impl.node.iface.InterfaceTransferResult AUTOCRAFTING_MISSING_RESOURCES;
    descriptor: Lcom/refinedmods/refinedstorage/api/network/impl/node/iface/InterfaceTransferResult;
    flags: (0x4019) ACC_PUBLIC, ACC_STATIC, ACC_FINAL, ACC_ENUM

  private static final com.refinedmods.refinedstorage.api.network.impl.node.iface.InterfaceTransferResult[] $VALUES;
    descriptor: [Lcom/refinedmods/refinedstorage/api/network/impl/node/iface/InterfaceTransferResult;
    flags: (0x101a) ACC_PRIVATE, ACC_STATIC, ACC_FINAL, ACC_SYNTHETIC

  public static com.refinedmods.refinedstorage.api.network.impl.node.iface.InterfaceTransferResult[] values();
    descriptor: ()[Lcom/refinedmods/refinedstorage/api/network/impl/node/iface/InterfaceTransferResult;
    flags: (0x0009) ACC_PUBLIC, ACC_STATIC
    Code:
      stack=1, locals=0, args_size=0
         0: getstatic     #19                 // Field $VALUES:[Lcom/refinedmods/refinedstorage/api/network/impl/node/iface/InterfaceTransferResult;
         3: invokevirtual #23                 // Method "[Lcom/refinedmods/refinedstorage/api/network/impl/node/iface/InterfaceTransferResult;".clone:()Ljava/lang/Object;
         6: checkcast     #24                 // class "[Lcom/refinedmods/refinedstorage/api/network/impl/node/iface/InterfaceTransferResult;"
         9: areturn
      LineNumberTable:
        line 3: 0

  public static com.refinedmods.refinedstorage.api.network.impl.node.iface.InterfaceTransferResult valueOf(java.lang.String);
    descriptor: (Ljava/lang/String;)Lcom/refinedmods/refinedstorage/api/network/impl/node/iface/InterfaceTransferResult;
    flags: (0x0009) ACC_PUBLIC, ACC_STATIC
    Code:
      stack=2, locals=1, args_size=1
         0: ldc           #1                  // class com/refinedmods/refinedstorage/api/network/impl/node/iface/InterfaceTransferResult
         2: aload_0
         3: invokestatic  #28                 // Method java/lang/Enum.valueOf:(Ljava/lang/Class;Ljava/lang/String;)Ljava/lang/Enum;
         6: checkcast     #1                  // class com/refinedmods/refinedstorage/api/network/impl/node/iface/InterfaceTransferResult
         9: areturn
      LineNumberTable:
        line 3: 0
      LocalVariableTable:
        Start  Length  Slot  Name   Signature
            0      10     0  name   Ljava/lang/String;
    MethodParameters:
      Name                           Flags
      <no name>                      mandated

  private com.refinedmods.refinedstorage.api.network.impl.node.iface.InterfaceTransferResult();
    descriptor: (Ljava/lang/String;I)V
    flags: (0x0002) ACC_PRIVATE
    Code:
      stack=3, locals=3, args_size=3
         0: aload_0
         1: aload_1
         2: iload_2
         3: invokespecial #34                 // Method java/lang/Enum."<init>":(Ljava/lang/String;I)V
         6: return
      LineNumberTable:
        line 3: 0
      LocalVariableTable:
        Start  Length  Slot  Name   Signature
            0       7     0  this   Lcom/refinedmods/refinedstorage/api/network/impl/node/iface/InterfaceTransferResult;
    MethodParameters:
      Name                           Flags
      <no name>                      synthetic
      <no name>                      synthetic
    Signature: #58                          // ()V

  private static com.refinedmods.refinedstorage.api.network.impl.node.iface.InterfaceTransferResult[] $values();
    descriptor: ()[Lcom/refinedmods/refinedstorage/api/network/impl/node/iface/InterfaceTransferResult;
    flags: (0x100a) ACC_PRIVATE, ACC_STATIC, ACC_SYNTHETIC
    Code:
      stack=4, locals=0, args_size=0
         0: iconst_5
         1: anewarray     #1                  // class com/refinedmods/refinedstorage/api/network/impl/node/iface/InterfaceTransferResult
         4: dup
         5: iconst_0
         6: getstatic     #3                  // Field EXPORTED:Lcom/refinedmods/refinedstorage/api/network/impl/node/iface/InterfaceTransferResult;
         9: aastore
        10: dup
        11: iconst_1
        12: getstatic     #7                  // Field RESOURCE_MISSING:Lcom/refinedmods/refinedstorage/api/network/impl/node/iface/InterfaceTransferResult;
        15: aastore
        16: dup
        17: iconst_2
        18: getstatic     #10                 // Field STORAGE_DOES_NOT_ACCEPT_RESOURCE:Lcom/refinedmods/refinedstorage/api/network/impl/node/iface/InterfaceTransferResult;
        21: aastore
        22: dup
        23: iconst_3
        24: getstatic     #13                 // Field AUTOCRAFTING_STARTED:Lcom/refinedmods/refinedstorage/api/network/impl/node/iface/InterfaceTransferResult;
        27: aastore
        28: dup
        29: iconst_4
        30: getstatic     #16                 // Field AUTOCRAFTING_MISSING_RESOURCES:Lcom/refinedmods/refinedstorage/api/network/impl/node/iface/InterfaceTransferResult;
        33: aastore
        34: areturn
      LineNumberTable:
        line 3: 0

  static {};
    descriptor: ()V
    flags: (0x0008) ACC_STATIC
    Code:
      stack=4, locals=0, args_size=0
         0: new           #1                  // class com/refinedmods/refinedstorage/api/network/impl/node/iface/InterfaceTransferResult
         3: dup
         4: ldc           #38                 // String EXPORTED
         6: iconst_0
         7: invokespecial #39                 // Method "<init>":(Ljava/lang/String;I)V
        10: putstatic     #3                  // Field EXPORTED:Lcom/refinedmods/refinedstorage/api/network/impl/node/iface/InterfaceTransferResult;
        13: new           #1                  // class com/refinedmods/refinedstorage/api/network/impl/node/iface/InterfaceTransferResult
        16: dup
        17: ldc           #40                 // String RESOURCE_MISSING
        19: iconst_1
        20: invokespecial #39                 // Method "<init>":(Ljava/lang/String;I)V
        23: putstatic     #7                  // Field RESOURCE_MISSING:Lcom/refinedmods/refinedstorage/api/network/impl/node/iface/InterfaceTransferResult;
        26: new           #1                  // class com/refinedmods/refinedstorage/api/network/impl/node/iface/InterfaceTransferResult
        29: dup
        30: ldc           #41                 // String STORAGE_DOES_NOT_ACCEPT_RESOURCE
        32: iconst_2
        33: invokespecial #39                 // Method "<init>":(Ljava/lang/String;I)V
        36: putstatic     #10                 // Field STORAGE_DOES_NOT_ACCEPT_RESOURCE:Lcom/refinedmods/refinedstorage/api/network/impl/node/iface/InterfaceTransferResult;
        39: new           #1                  // class com/refinedmods/refinedstorage/api/network/impl/node/iface/InterfaceTransferResult
        42: dup
        43: ldc           #42                 // String AUTOCRAFTING_STARTED
        45: iconst_3
        46: invokespecial #39                 // Method "<init>":(Ljava/lang/String;I)V
        49: putstatic     #13                 // Field AUTOCRAFTING_STARTED:Lcom/refinedmods/refinedstorage/api/network/impl/node/iface/InterfaceTransferResult;
        52: new           #1                  // class com/refinedmods/refinedstorage/api/network/impl/node/iface/InterfaceTransferResult
        55: dup
        56: ldc           #43                 // String AUTOCRAFTING_MISSING_RESOURCES
        58: iconst_4
        59: invokespecial #39                 // Method "<init>":(Ljava/lang/String;I)V
        62: putstatic     #16                 // Field AUTOCRAFTING_MISSING_RESOURCES:Lcom/refinedmods/refinedstorage/api/network/impl/node/iface/InterfaceTransferResult;
        65: invokestatic  #44                 // Method $values:()[Lcom/refinedmods/refinedstorage/api/network/impl/node/iface/InterfaceTransferResult;
        68: putstatic     #19                 // Field $VALUES:[Lcom/refinedmods/refinedstorage/api/network/impl/node/iface/InterfaceTransferResult;
        71: return
      LineNumberTable:
        line 4: 0
        line 5: 13
        line 6: 26
        line 7: 39
        line 8: 52
        line 3: 65
}
Signature: #60                          // Ljava/lang/Enum<Lcom/refinedmods/refinedstorage/api/network/impl/node/iface/InterfaceTransferResult;>;
SourceFile: "InterfaceTransferResult.java"
